alibabacloud_imageprocess20200320/__init__.py
alibabacloud_imageprocess20200320/client.py
alibabacloud_imageprocess20200320/models.py
alibabacloud_imageprocess20200320-2.3.0.dist-info/LICENSE
alibabacloud_imageprocess20200320-2.3.0.dist-info/METADATA
alibabacloud_imageprocess20200320-2.3.0.dist-info/WHEEL
alibabacloud_imageprocess20200320-2.3.0.dist-info/top_level.txt
alibabacloud_imageprocess20200320-2.3.0.dist-info/RECORD
