Metadata-Version: 2.1
Name: alibabacloud-imageprocess20200320
Version: 2.3.0
Summary: Alibaba Cloud imageprocess (20200320) SDK Library for Python
Home-page: https://github.com/aliyun/alibabacloud-python-sdk
Author: Alibaba Cloud SDK
Author-email: sdk-team@alibabacloud.com
License: Apache License 2.0
Keywords: alibabacloud,imageprocess20200320
Platform: any
Classifier: Development Status :: 4 - Beta
Classifier: Intended Audience :: Developers
Classifier: License :: OSI Approved :: Apache Software License
Classifier: Programming Language :: Python
Classifier: Programming Language :: Python :: 3
Classifier: Programming Language :: Python :: 3.6
Classifier: Programming Language :: Python :: 3.7
Classifier: Programming Language :: Python :: 3.8
Classifier: Programming Language :: Python :: 3.9
Classifier: Topic :: Software Development
Requires-Python: >=3.6
License-File: LICENSE
Requires-Dist: alibabacloud-darabonba-number (<1.0.0,>=0.0.4)
Requires-Dist: alibabacloud-endpoint-util (<1.0.0,>=0.0.3)
Requires-Dist: alibabacloud-openapi-util (<1.0.0,>=0.2.2)
Requires-Dist: alibabacloud-openplatform20191219 (<3.0.0,>=2.0.0)
Requires-Dist: alibabacloud-oss-sdk (<1.0.0,>=0.1.1)
Requires-Dist: alibabacloud-oss-util (<1.0.0,>=0.0.5)
Requires-Dist: alibabacloud-tea-fileform (<1.0.0,>=0.0.3)
Requires-Dist: alibabacloud-tea-openapi (<1.0.0,>=0.3.15)
Requires-Dist: alibabacloud-tea-util (<1.0.0,>=0.3.13)
